README.md
README.txt
setup.py
lobsteronaws/__init__.py
lobsteronaws.egg-info/PKG-INFO
lobsteronaws.egg-info/SOURCES.txt
lobsteronaws.egg-info/dependency_links.txt
lobsteronaws.egg-info/top_level.txt
lobsteronaws/aws/__init__.py
lobsteronaws/aws/emr.py
lobsteronaws/demo/__init__.py
lobsteronaws/demo/construct_order_book.py
lobsteronaws/demo/lobster_demo.py
lobsteronaws/lobster/__init__.py
lobsteronaws/lobster/functions.py
lobsteronaws/lobster/order_book.py
lobsteronaws/tests/__init__.py
lobsteronaws/tests/test_functions.py
lobsteronaws/tests/test_order_book.py