Metadata-Version: 2.1
Name: lobsteronaws
Version: 0.1.2
Summary: UNKNOWN
Home-page: https://github.com/vonde-consulting/lobsteronaws
Author: Ruihong Huang
Author-email: huang@lobsterdata.com
License: MIT License
Platform: UNKNOWN
